urlprofiler/__init__.py
urlprofiler/http/__init__.py
urlprofiler/http/request.py
urlprofiler/profile/__init__.py
urlprofiler/profile/profile_url.py
urlprofiler/ssl/__init__.py
urlprofiler/ssl/cert_info.py
urlprofiler/url/__init__.py
urlprofiler/url/validator.py
urlprofiler-1.5.2.dist-info/LICENSE
urlprofiler-1.5.2.dist-info/METADATA
urlprofiler-1.5.2.dist-info/WHEEL
urlprofiler-1.5.2.dist-info/entry_points.txt
urlprofiler-1.5.2.dist-info/top_level.txt
urlprofiler-1.5.2.dist-info/RECORD
