Metadata-Version: 2.1
Name: urlprofiler
Version: 1.5.2
Summary: Fetches available metadata about a URL
Author-email: Alex Pope <67066474+aroundwithalex@users.noreply.github.com>
Project-URL: Homepage, https://github.com/aroundwithalex/urlprofile
Project-URL: Bug Tracker, https://github.com/aroundwithalex/urlprofile/issues
Classifier: Programming Language :: Python :: 3
Classifier: License :: OSI Approved :: MIT License
Classifier: Operating System :: OS Independent
Requires-Python: >=3.7
License-File: LICENSE
Requires-Dist: httpx (>=0.23.0)
Requires-Dist: tldextract (>=3.4.0)
